movies_etl-0.1.3.dist-info/METADATA
movies_etl-0.1.3.dist-info/WHEEL
movies_etl-0.1.3.dist-info/entry_points.txt
movies_etl/__init__.py
movies_etl/api/__init__.py
movies_etl/api/call.py
movies_etl-0.1.3.dist-info/RECORD
