Metadata-Version: 2.1
Name: movies-etl
Version: 0.1.3
Summary: Default template for PDM package
Author-Email: vhzkclq0705 <vhzkclq0705@naver.com>
License: MIT
Requires-Python: >=3.10
Requires-Dist: requests>=2.32.3
Requires-Dist: pandas>=2.2.3
Requires-Dist: pyarrow>=19.0.1
Requires-Dist: python-dotenv>=1.0.1
